Workbook

Sheet Dashboard
A1: Lead Pipeline Dashboard
A2: Updates automatically from the Leads and Call Log sheets. Charts fill in as you log calls and set Lead Status.
A4: Total Leads | B4: Calls Made | C4: Leads Contacted | D4: Interested / Meeting | E4: Converted | F4: Conversion Rate | H4: Revenue Won (Rs) | I4: No-Website Leads
A5: =COUNTA(Leads!$A$5:$A$400) -> 102 | B5: =SUM(Leads!$T$5:$T$400) -> 0 | C5: =COUNTIF(Leads!$T$5:$T$400,">0") -> 0 | D5: =COUNTIF(Leads!$S$5:$S$400,"Interested")+COUNTIF(Leads!$S$5:$S$400,"Meeting / Proposal Sent") -> 0 | E5: =COUNTIF(Leads!$S$5:$S$400,"Converted") -> 0 | F5: =IFERROR(E5/C5,0) -> 0 | H5: =SUMIFS(Leads!$W$5:$W$400,Leads!$S$5:$S$400,"Converted") -> 0 | I5: =COUNTIF(Leads!$M$5:$M$400,"No website*") -> 68
A6: Conversion rate = Converted / Leads Contacted.
A8: Performance by Niche | H8: Call Outcomes (all calls) | K8: Contacted Leads: Converted vs Not
A9: Niche | B9: Leads | C9: Calls Made | D9: Contacted | E9: Converted | F9: Conv. Rate | H9: Outcome | I9: Calls | K9: Result | L9: Leads
A10: Solar Installation | B10: =COUNTIF(Leads!$B$5:$B$400,A10) -> 26 | C10: =SUMIFS(Leads!$T$5:$T$400,Leads!$B$5:$B$400,A10) -> 0 | D10: =COUNTIFS(Leads!$B$5:$B$400,A10,Leads!$T$5:$T$400,">0") -> 0 | E10: =COUNTIFS(Leads!$B$5:$B$400,A10,Leads!$S$5:$S$400,"Converted") -> 0 | F10: =IFERROR(E10/D10,0) -> 0 | H10: No Answer | I10: =COUNTIF('Call Log'!$E$5:$E$1000,H10) -> 0 | K10: Converted | L10: =E5 -> 0
A11: Spice Brand | B11: =COUNTIF(Leads!$B$5:$B$400,A11) -> 12 | C11: =SUMIFS(Leads!$T$5:$T$400,Leads!$B$5:$B$400,A11) -> 0 | D11: =COUNTIFS(Leads!$B$5:$B$400,A11,Leads!$T$5:$T$400,">0") -> 0 | E11: =COUNTIFS(Leads!$B$5:$B$400,A11,Leads!$S$5:$S$400,"Converted") -> 0 | F11: =IFERROR(E11/D11,0) -> 0 | H11: Call Back Later | I11: =COUNTIF('Call Log'!$E$5:$E$1000,H11) -> 0 | K11: Not converted yet | L11: =MAX(C5-E5,0) -> 0
A12: Food Manufacturer | B12: =COUNTIF(Leads!$B$5:$B$400,A12) -> 19 | C12: =SUMIFS(Leads!$T$5:$T$400,Leads!$B$5:$B$400,A12) -> 0 | D12: =COUNTIFS(Leads!$B$5:$B$400,A12,Leads!$T$5:$T$400,">0") -> 0 | E12: =COUNTIFS(Leads!$B$5:$B$400,A12,Leads!$S$5:$S$400,"Converted") -> 0 | F12: =IFERROR(E12/D12,0) -> 0 | H12: Interested | I12: =COUNTIF('Call Log'!$E$5:$E$1000,H12) -> 0 | K12: Not contacted | L12: =MAX(A5-C5,0) -> 102
A13: Interior Design | B13: =COUNTIF(Leads!$B$5:$B$400,A13) -> 23 | C13: =SUMIFS(Leads!$T$5:$T$400,Leads!$B$5:$B$400,A13) -> 0 | D13: =COUNTIFS(Leads!$B$5:$B$400,A13,Leads!$T$5:$T$400,">0") -> 0 | E13: =COUNTIFS(Leads!$B$5:$B$400,A13,Leads!$S$5:$S$400,"Converted") -> 0 | F13: =IFERROR(E13/D13,0) -> 0 | H13: Meeting Booked | I13: =COUNTIF('Call Log'!$E$5:$E$1000,H13) -> 0
A14: Furniture Shop | B14: =COUNTIF(Leads!$B$5:$B$400,A14) -> 22 | C14: =SUMIFS(Leads!$T$5:$T$400,Leads!$B$5:$B$400,A14) -> 0 | D14: =COUNTIFS(Leads!$B$5:$B$400,A14,Leads!$T$5:$T$400,">0") -> 0 | E14: =COUNTIFS(Leads!$B$5:$B$400,A14,Leads!$S$5:$S$400,"Converted") -> 0 | F14: =IFERROR(E14/D14,0) -> 0 | H14: Proposal Sent | I14: =COUNTIF('Call Log'!$E$5:$E$1000,H14) -> 0 | K14: Lead Status
A15: Total | B15: =SUM(B10:B14) -> 102 | C15: =SUM(C10:C14) -> 0 | D15: =SUM(D10:D14) -> 0 | E15: =SUM(E10:E14) -> 0 | F15: =IFERROR(E15/D15,0) -> 0 | H15: Converted | I15: =COUNTIF('Call Log'!$E$5:$E$1000,H15) -> 0 | K15: Status | L15: Leads
H16: Not Interested | I16: =COUNTIF('Call Log'!$E$5:$E$1000,H16) -> 0 | K16: Not Contacted | L16: =COUNTIF(Leads!$S$5:$S$400,K16) -> 102
H17: Wrong / Invalid Number | I17: =COUNTIF('Call Log'!$E$5:$E$1000,H17) -> 0 | K17: Called - No Answer | L17: =COUNTIF(Leads!$S$5:$S$400,K17) -> 0
H18: Total | I18: =SUM(I10:I17) -> 0 | K18: Called - Call Back Later | L18: =COUNTIF(Leads!$S$5:$S$400,K18) -> 0
K19: Interested | L19: =COUNTIF(Leads!$S$5:$S$400,K19) -> 0
K20: Meeting / Proposal Sent | L20: =COUNTIF(Leads!$S$5:$S$400,K20) -> 0
K21: Converted | L21: =COUNTIF(Leads!$S$5:$S$400,K21) -> 0
K22: Not Interested | L22: =COUNTIF(Leads!$S$5:$S$400,K22) -> 0
K23: Invalid Number | L23: =COUNTIF(Leads!$S$5:$S$400,K23) -> 0
A25: Charts

Sheet Leads
A1: Dezmos Digital Marketing - Trivandrum Website Leads
A2: Niches: solar installation, spice brands, food manufacturers, interior design, furniture shops. Edit only the lime-tinted columns (Lead Status, Next Follow-up, Deal Value, Notes) and log every call in 'Call Log'. Calls Made and Last Call Date fill in automatically.
A4: Lead ID | B4: Niche | C4: Business Name | D4: Owner / Decision Maker | E4: Area | F4: Address | G4: Primary Phone | H4: Phone Type | I4: WhatsApp | J4: Alt / Office Phone | K4: Email | L4: Website | M4: Website Status | N4: Rating | O4: Lead Source | P4: Source URL | Q4: Main Pitch | R4: Priority | S4: Lead Status | T4: Calls Made | U4: Last Call Date | V4: Next Follow-up | W4: Deal Value (Rs) | X4: Notes
A5: TVM-001 | B5: Solar Installation | C5: Aadithya Innovations Solar | D5: Not listed - ask on call / MCA | E5: Pappanamcode | F5: TC 56/60, 10, SRK Building, Pappanamcode, TVM 695018 | G5: 08490040914 | H5: Justdial virtual no. (routes to owner) | I5: Use Justdial chat; ask for WhatsApp no. | J5: - | K5: - | L5: aadithyainnovations.com | M5: Has website - audit conversions | N5: 4.9 (129) Justdial | O5: Justdial + ENF Solar | P5: https://www.justdial.com/Thiruvananthapuram/Residential-Solar-Panel-Installation-Services/nct-12154454 | Q5: Turn the site into a lead engine: subsidy + savings calculator, KSEB/MNRE empanelment proof, installed-project gallery (kW, savings/month), Google reviews and click-to-WhatsApp, with enquiry tracking so you can see cost per lead. Hook: Strong 4.9 rating with 129 reviews - showcase it on the site to convert visitors. | R5: Warm | S5: Not Contacted | T5: =COUNTIF('Call Log'!$B:$B,A5) -> 0 | U5: =IF(T5=0,"",_xlfn.MAXIFS('Call Log'!$A:$A,'Call Log'!$B:$B,A5))
A6: TVM-002 | B6: Solar Installation | C6: Anand Solar (TATA Power Solar Distributor) | D6: Not listed - ask on call / MCA | E6: Peyad | F6: Peyad, Thiruvananthapuram | G6: 08128463201 | H6: Justdial virtual no. (routes to owner) | I6: Use Justdial chat; ask for WhatsApp no. | J6: - | K6: - | L6: - | M6: No website found | N6: 4.9 Justdial | O6: Justdial | P6: https://www.justdial.com/Thiruvananthapuram/Residential-Solar-Panel-Installation-Services/nct-12154454 | Q6: No website: launch a PM Surya Ghar / KSEB Soura subsidy landing page with a rooftop savings calculator and a WhatsApp 'Get free site survey' button, so homeowners searching 'solar subsidy Trivandrum' reach you directly instead of Justdial competitors. Hook: TATA Power brand authority but no own website - competitors outrank them on Google. | R6: Warm | S6: Not Contacted | T6: =COUNTIF('Call Log'!$B:$B,A6) -> 0 | U6: =IF(T6=0,"",_xlfn.MAXIFS('Call Log'!$A:$A,'Call Log'!$B:$B,A6))
A7: TVM-003 | B7: Solar Installation | C7: Micro Smart Technologies | D7: Not listed - ask on call / MCA | E7: Peyad | F7: Peyad, Thiruvananthapuram | G7: 08460307105 | H7: Justdial virtual no. (routes to owner) | I7: Use Justdial chat; ask for WhatsApp no. | J7: - | K7: - | L7: - | M7: No website found | N7: - | O7: Justdial | P7: https://www.justdial.com/Thiruvananthapuram/Residential-Solar-Panel-Installation-Services/nct-12154454 | Q7: No website: launch a PM Surya Ghar / KSEB Soura subsidy landing page with a rooftop savings calculator and a WhatsApp 'Get free site survey' button, so homeowners searching 'solar subsidy Trivandrum' reach you directly instead of Justdial competitors. | R7: Warm | S7: Not Contacted | T7: =COUNTIF('Call Log'!$B:$B,A7) -> 0 | U7: =IF(T7=0,"",_xlfn.MAXIFS('Call Log'!$A:$A,'Call Log'!$B:$B,A7))
A8: TVM-004 | B8: Solar Installation | C8: Hello Solar Energy Solutions | D8: Not listed - ask on call / MCA | E8: Varkala | F8: Varkala, Thiruvananthapuram district | G8: 08460530606 | H8: Justdial virtual no. (routes to owner) | I8: Use Justdial chat; ask for WhatsApp no. | J8: - | K8: - | L8: - | M8: No website found | N8: - | O8: Justdial | P8: https://www.justdial.com/Thiruvananthapuram/Residential-Solar-Panel-Installation-Services/nct-12154454 | Q8: No website: launch a PM Surya Ghar / KSEB Soura subsidy landing page with a rooftop savings calculator and a WhatsApp 'Get free site survey' button, so homeowners searching 'solar subsidy Trivandrum' reach you directly instead of Justdial competitors. Hook: Varkala homestays/resorts are a high-ticket solar segment - landing page for them. | R8: Warm | S8: Not Contacted | T8: =COUNTIF('Call Log'!$B:$B,A8) -> 0 | U8: =IF(T8=0,"",_xlfn.MAXIFS('Call Log'!$A:$A,'Call Log'!$B:$B,A8))
A9: TVM-005 | B9: Solar Installation | C9: V Power Solutions | D9: Not listed - ask on call / MCA | E9: Attukal | F9: Attukal, Thiruvananthapuram | G9: 09972269871 | H9: Justdial virtual no. (routes to owner) | I9: Use Justdial chat; ask for WhatsApp no. | J9: - | K9: - | L9: - | M9: No website found | N9: - | O9: Justdial | P9: https://www.justdial.com/Thiruvananthapuram/Residential-Solar-Panel-Installation-Services/nct-12154454 | Q9: No website: launch a PM Surya Ghar / KSEB Soura subsidy landing page with a rooftop savings calculator and a WhatsApp 'Get free site survey' button, so homeowners searching 'solar subsidy Trivandrum' reach you directly instead of Justdial competitors. | R9: Warm | S9: Not Contacted | T9: =COUNTIF('Call Log'!$B:$B,A9) -> 0 | U9: =IF(T9=0,"",_xlfn.MAXIFS('Call Log'!$A:$A,'Call Log'!$B:$B,A9))
A10: TVM-006 | B10: Solar Installation | C10: Rudraveena Solar & Home Solutions | D10: Not listed - ask on call / MCA | E10: Naruvamoodu | F10: Naruvamoodu, Thiruvananthapuram | G10: +91 85900 02123 | H10: Direct mobile | I10: +91 85900 02123 (likely - verify) | J10: 09606167175 (Justdial) | K10: contact@rudraveenasolutions.com | L10: rudraveenasolutions.com | M10: Has website - audit conversions | N10: - | O10: Website + Justdial | P10: https://www.rudraveenasolutions.com/ | Q10: Turn the site into a lead engine: subsidy + savings calculator, KSEB/MNRE empanelment proof, installed-project gallery (kW, savings/month), Google reviews and click-to-WhatsApp, with enquiry tracking so you can see cost per lead. Hook: Claims KSEB empanelment - make subsidy eligibility the hero of the site. | R10: Warm | S10: Not Contacted | T10: =COUNTIF('Call Log'!$B:$B,A10) -> 0 | U10: =IF(T10=0,"",_xlfn.MAXIFS('Call Log'!$A:$A,'Call Log'!$B:$B,A10))
A11: TVM-007 | B11: Solar Installation | C11: Univarsa Techies Pvt Ltd | D11: Not listed - ask on call / MCA | E11: Enjakkal | F11: Enjakkal, Thiruvananthapuram | G11: 09008359088 | H11: Justdial virtual no. (routes to owner) | I11: Use Justdial chat; ask for WhatsApp no. | J11: - | K11: - | L11: - | M11: No website found | N11: - | O11: Justdial | P11: https://www.justdial.com/Thiruvananthapuram/Residential-Solar-Panel-Installation-Services/nct-12154454 | Q11: No website: launch a PM Surya Ghar / KSEB Soura subsidy landing page with a rooftop savings calculator and a WhatsApp 'Get free site survey' button, so homeowners searching 'solar subsidy Trivandrum' reach you directly instead of Justdial competitors. | R11: Warm | S11: Not Contacted | T11: =COUNTIF('Call Log'!$B:$B,A11) -> 0 | U11: =IF(T11=0,"",_xlfn.MAXIFS('Call Log'!$A:$A,'Call Log'!$B:$B,A11))
A12: TVM-008 | B12: Solar Installation | C12: Light Sky International Pvt Ltd | D12: Not listed - ask on call / MCA | E12: Jagathy | F12: Sree Rudram, Jagathy, TVM 695014 | G12: +91 73562 13562 | H12: Direct mobile | I12: +91 73562 13562 (likely - verify) | J12: 08460379701 (Justdial) | K12: info@lightskyinternational.com | L12: lightskyinternational.com | M12: Has website - audit conversions | N12: - | O12: Website + Justdial | P12: https://lightskyinternational.com/ | Q12: Turn the site into a lead engine: subsidy + savings calculator, KSEB/MNRE empanelment proof, installed-project gallery (kW, savings/month), Google reviews and click-to-WhatsApp, with enquiry tracking so you can see cost per lead. | R12: Warm | S12: Not Contacted | T12: =COUNTIF('Call Log'!$B:$B,A12) -> 0 | U12: =IF(T12=0,"",_xlfn.MAXIFS('Call Log'!$A:$A,'Call Log'!$B:$B,A12))
A13: TVM-009 | B13: Solar Installation | C13: Wattsun Energy | D13: Not listed - ask on call / MCA | E13: Chackai | F13: Airport Road, Chackai, Thiruvananthapuram | G13: +91 93881 06363 | H13: Direct mobile | I13: +91 93881 06363 (likely - verify) | J13: +91 89433 45706 | K13: sourawattsun@gmail.com | L13: - | M13: No website (Gmail only) | N13: - | O13: KSEB Soura empanelled list | P13: https://ekiran.kseb.in/documents/2%20and%20upto%203.pdf | Q13: No website: launch a PM Surya Ghar / KSEB Soura subsidy landing page with a rooftop savings calculator and a WhatsApp 'Get free site survey' button, so homeowners searching 'solar subsidy Trivandrum' reach you directly instead of Justdial competitors. Hook: KSEB Soura empanelled but only a Gmail ID - no website to capture subsidy searches. | R13: Hot | S13: Not Contacted | T13: =COUNTIF('Call Log'!$B:$B,A13) -> 0 | U13: =IF(T13=0,"",_xlfn.MAXIFS('Call Log'!$A:$A,'Call Log'!$B:$B,A13))
A14: TVM-010 | B14: Solar Installation | C14: Renergy Systems | D14: Not listed - ask on call / MCA | E14: Attingal | F14: Attingal, Thiruvananthapuram district | G14: +91 70343 22221 | H14: Direct mobile | I14: +91 70343 22221 (likely - verify) | J14: +91 96453 22221 | K14: soura.renergysales@gmail.com | L14: - | M14: No website (Gmail only) | N14: - | O14: KSEB Soura empanelled list | P14: https://ekiran.kseb.in/documents/2%20and%20upto%203.pdf | Q14: No website: launch a PM Surya Ghar / KSEB Soura subsidy landing page with a rooftop savings calculator and a WhatsApp 'Get free site survey' button, so homeowners searching 'solar subsidy Trivandrum' reach you directly instead of Justdial competitors. Hook: KSEB Soura empanelled but only a Gmail ID - no website. | R14: Hot | S14: Not Contacted | T14: =COUNTIF('Call Log'!$B:$B,A14) -> 0 | U14: =IF(T14=0,"",_xlfn.MAXIFS('Call Log'!$A:$A,'Call Log'!$B:$B,A14))
A15: TVM-011 | B15: Solar Installation | C15: BSS Solar Kerala | D15: Not listed - ask on call / MCA | E15: Kowdiar | F15: Brahmins Colony, Kowdiar PO, TVM 695003 | G15: 0471-2439322 | H15: Office landline | I15: 9048001332 | J15: 9048001332 | K15: bsssolarkerala@gmail.com | L15: bsssolar.com | M15: Has website - audit conversions | N15: - | O15: Company website | P15: https://bsssolar.com/ | Q15: Turn the site into a lead engine: subsidy + savings calculator, KSEB/MNRE empanelment proof, installed-project gallery (kW, savings/month), Google reviews and click-to-WhatsApp, with enquiry tracking so you can see cost per lead. | R15: Warm | S15: Not Contacted | T15: =COUNTIF('Call Log'!$B:$B,A15) -> 0 | U15: =IF(T15=0,"",_xlfn.MAXIFS('Call Log'!$A:$A,'Call Log'!$B:$B,A15))
A16: TVM-012 | B16: Solar Installation | C16: OnGrid Solar Power Solutions Pvt Ltd | D16: Not listed - ask on call / MCA | E16: Vattiyoorkavu | F16: Vattiyoorkavu, Thiruvananthapuram | G16: +91 75949 49406 | H16: Direct mobile | I16: +91 75949 49406 (likely - verify) | J16: - | K16: ongridsolarpowersolution@gmail.com | L16: ongridsolarpowersolutions.com | M16: Has website - audit conversions | N16: - | O16: Company website | P16: https://www.ongridsolarpowersolutions.com/ | Q16: Turn the site into a lead engine: subsidy + savings calculator, KSEB/MNRE empanelment proof, installed-project gallery (kW, savings/month), Google reviews and click-to-WhatsApp, with enquiry tracking so you can see cost per lead. Hook: Advertises up to Rs 78,000 subsidy - build a subsidy calculator funnel around it. | R16: Warm | S16: Not Contacted | T16: =COUNTIF('Call Log'!$B:$B,A16) -> 0 | U16: =IF(T16=0,"",_xlfn.MAXIFS('Call Log'!$A:$A,'Call Log'!$B:$B,A16))
... A106: TVM-102 | B106: Furniture Shop | C106: Evernest Industries | D106: Not listed - ask on call / MCA | E106: Nedumangad | F106: Nedumangad, Thiruvananthapuram district | G106: - | H106: Not public - find via website / visit | I106: - | J106: - | K106: - | L106: - | M106: No website found | N106: - | O106: IndiaMART | P106: https://dir.indiamart.com/thiruvananthapuram/wooden-furniture.html | Q106: No website: online catalogue with price ranges and an 'Enquire on WhatsApp' button per product, showroom map and offers page, so Instagram/Google browsers turn into showroom visits. Hook: Manufacturer/wholesaler. | R106: Cold | S106: Not Contacted | T106: =COUNTIF('Call Log'!$B:$B,A106) -> 0 | U106: =IF(T106=0,"",_xlfn.MAXIFS('Call Log'!$A:$A,'Call Log'!$B:$B,A106))

Sheet Call Log
A1: Call Log - one row per call
A2: Enter Date, Lead ID (e.g. TVM-001), Outcome and notes. Business and Niche fill in automatically. The grey row 4 is an example and is not counted (its ID does not match any lead).
A3: Date | B3: Lead ID | C3: Business (auto) | D3: Niche (auto) | E3: Call Outcome | F3: Spoke With | G3: Next Step | H3: Follow-up Date | I3: Notes
A4: 46316 | B4: EXAMPLE | C4: Example Solar Pvt Ltd | D4: Solar Installation | E4: Call Back Later | F4: Owner (Mr. Name) | G4: Send WhatsApp portfolio | H4: 46318 | I4: Asked to call after 5 pm
C5: =IF(B5="","",IFERROR(INDEX(Leads!$C:$C,MATCH(B5,Leads!$A:$A,0)),"ID not found")) | D5: =IF(B5="","",IFERROR(INDEX(Leads!$B:$B,MATCH(B5,Leads!$A:$A,0)),""))
C6: =IF(B6="","",IFERROR(INDEX(Leads!$C:$C,MATCH(B6,Leads!$A:$A,0)),"ID not found")) | D6: =IF(B6="","",IFERROR(INDEX(Leads!$B:$B,MATCH(B6,Leads!$A:$A,0)),""))
C7: =IF(B7="","",IFERROR(INDEX(Leads!$C:$C,MATCH(B7,Leads!$A:$A,0)),"ID not found")) | D7: =IF(B7="","",IFERROR(INDEX(Leads!$B:$B,MATCH(B7,Leads!$A:$A,0)),""))
C8: =IF(B8="","",IFERROR(INDEX(Leads!$C:$C,MATCH(B8,Leads!$A:$A,0)),"ID not found")) | D8: =IF(B8="","",IFERROR(INDEX(Leads!$B:$B,MATCH(B8,Leads!$A:$A,0)),""))
C9: =IF(B9="","",IFERROR(INDEX(Leads!$C:$C,MATCH(B9,Leads!$A:$A,0)),"ID not found")) | D9: =IF(B9="","",IFERROR(INDEX(Leads!$B:$B,MATCH(B9,Leads!$A:$A,0)),""))
C10: =IF(B10="","",IFERROR(INDEX(Leads!$C:$C,MATCH(B10,Leads!$A:$A,0)),"ID not found")) | D10: =IF(B10="","",IFERROR(INDEX(Leads!$B:$B,MATCH(B10,Leads!$A:$A,0)),""))
C11: =IF(B11="","",IFERROR(INDEX(Leads!$C:$C,MATCH(B11,Leads!$A:$A,0)),"ID not found")) | D11: =IF(B11="","",IFERROR(INDEX(Leads!$B:$B,MATCH(B11,Leads!$A:$A,0)),""))
C12: =IF(B12="","",IFERROR(INDEX(Leads!$C:$C,MATCH(B12,Leads!$A:$A,0)),"ID not found")) | D12: =IF(B12="","",IFERROR(INDEX(Leads!$B:$B,MATCH(B12,Leads!$A:$A,0)),""))
C13: =IF(B13="","",IFERROR(INDEX(Leads!$C:$C,MATCH(B13,Leads!$A:$A,0)),"ID not found")) | D13: =IF(B13="","",IFERROR(INDEX(Leads!$B:$B,MATCH(B13,Leads!$A:$A,0)),""))
C14: =IF(B14="","",IFERROR(INDEX(Leads!$C:$C,MATCH(B14,Leads!$A:$A,0)),"ID not found")) | D14: =IF(B14="","",IFERROR(INDEX(Leads!$B:$B,MATCH(B14,Leads!$A:$A,0)),""))
C15: =IF(B15="","",IFERROR(INDEX(Leads!$C:$C,MATCH(B15,Leads!$A:$A,0)),"ID not found")) | D15: =IF(B15="","",IFERROR(INDEX(Leads!$B:$B,MATCH(B15,Leads!$A:$A,0)),""))
C16: =IF(B16="","",IFERROR(INDEX(Leads!$C:$C,MATCH(B16,Leads!$A:$A,0)),"ID not found")) | D16: =IF(B16="","",IFERROR(INDEX(Leads!$B:$B,MATCH(B16,Leads!$A:$A,0)),""))
... C1000: =IF(B1000="","",IFERROR(INDEX(Leads!$C:$C,MATCH(B1000,Leads!$A:$A,0)),"ID not found")) | D1000: =IF(B1000="","",IFERROR(INDEX(Leads!$B:$B,MATCH(B1000,Leads!$A:$A,0)),""))

Sheet Pitch Playbook
A1: Pitch Playbook - website development
A3: Niche | B3: Core pitch (no website) | C3: Core pitch (has website, not converting) | D3: WhatsApp / call opener | E3: Objection -> answer
A4: Solar Installation | B4: No website: launch a PM Surya Ghar / KSEB Soura subsidy landing page with a rooftop savings calculator and a WhatsApp 'Get free site survey' button, so homeowners searching 'solar subsidy Trivandrum' reach you directly instead of Justdial competitors. | C4: Turn the site into a lead engine: subsidy + savings calculator, KSEB/MNRE empanelment proof, installed-project gallery (kW, savings/month), Google reviews and click-to-WhatsApp, with enquiry tracking so you can see cost per lead. | D4: Hi [Name], this is [Your Name] from Dezmos Digital Marketing, Trivandrum. People here search 'solar subsidy Trivandrum' every day. We build solar websites with a subsidy calculator that send enquiries straight to your WhatsApp. Can I show you a 2-minute demo? | E4: 'We get leads from Justdial' -> Justdial shares each lead with 3-5 competitors. Your own site gives you leads nobody else gets.
A5: Spice Brand | B5: No website: branded D2C store with UPI checkout, WhatsApp ordering and a bulk/distributor enquiry page, so retailers and NRI buyers can find and order without going through IndiaMART. | C5: Make the site sell: product pages with recipes, online checkout + Amazon/Flipkart links, FSSAI and quality proof, and separate retail / distributor / export enquiry forms. | D5: Hi [Name], [Your Name] from Dezmos, Trivandrum. Your masalas could sell online to NRI and pan-India buyers. We set up spice brand stores with UPI checkout and WhatsApp ordering. Open to a quick look? | E5: 'Distributors handle sales' -> A site supports distributors with a catalogue, and adds direct online orders with better margins.
A6: Food Manufacturer | B6: No website: B2B catalogue site (product specs, MOQ, pack sizes, FSSAI, export readiness) with a distributor enquiry form, to win supermarket/export buyers and cut dependence on paid IndiaMART leads. | C6: Upgrade to a distributor-lead funnel: downloadable catalogue, enquiry form with MOQ/location, retailer locator, export page and WhatsApp CTA; track enquiries per month. | D6: Hi [Name], [Your Name] from Dezmos. Supermarket and export buyers check a manufacturer's website before placing orders. We build B2B catalogue sites with distributor enquiry forms. Could I send a sample? | E6: 'IndiaMART is enough' -> IndiaMART leads are paid and shared. A site plus Google listing brings direct buyers at no per-lead cost.
A7: Interior Design | B7: No website: portfolio site with project galleries, a 2BHK/3BHK cost estimator and a 'Book free consultation' form, plus Google reviews, so new homeowners shortlist you before calling competitors. | C7: Most interior sites show photos but don't capture leads: add a BHK cost estimator, before/after case studies with budgets, review widget, sticky WhatsApp CTA and a consultation booking calendar. | D7: Hi [Name], [Your Name] from Dezmos, Trivandrum. Homeowners shortlist interior firms online before calling. We build portfolio sites with a BHK cost estimator that books consultations for you. Can I show you one? | E7: 'Instagram is enough' -> Instagram shows work; a site with an estimator and booking form captures the enquiry and ranks on Google.
A8: Furniture Shop | B8: No website: online catalogue with price ranges and an 'Enquire on WhatsApp' button per product, showroom map and offers page, so Instagram/Google browsers turn into showroom visits. | C8: Make the catalogue convert: price ranges, WhatsApp enquiry per product, festival-offer landing pages, EMI info and showroom-visit booking, linked to your Google Business profile. | D8: Hi [Name], [Your Name] from Dezmos. Buyers browse furniture online before visiting a showroom. We build catalogue sites with a WhatsApp enquiry button on every product. Can I share an example? | E8: 'Customers walk in anyway' -> Most buyers check online first. A catalogue sends them to your showroom instead of the chain stores.
A10: Website audit checklist (before pitching a 'has website' lead)
A11: 1. | B11: Opens fast on mobile (under 3 seconds)?
A12: 2. | B12: Click-to-call and WhatsApp button visible on every page?
A13: 3. | B13: Enquiry form above the fold, short (3-4 fields)?
A14: 4. | B14: Proof shown: reviews, certifications, project photos with numbers?
A15: 5. | B15: Google Business profile linked and consistent (name, phone, address)?
A16: 6. | B16: Ranks for '[service] Trivandrum' on Google?
A17: 7. | B17: SSL (https) and up-to-date content (no old offers / dead links)?
A18: 8. | B18: Any enquiry tracking (Analytics, form notifications)?
A20: Compliance note: these are publicly listed business contacts. Call in business hours, honour 'do not contact' requests, and avoid bulk unsolicited WhatsApp messages (TRAI / WhatsApp Business policy).

Sheet Sources & Notes
A1: How these leads were collected
A2: Researched on 20 Oct 2026 from public business listings: Justdial, IndiaMART, TradeIndia, ExportersIndia, ENF Solar, KSEB Soura empanelled list, Quickerala, yappe.in, Dun & Bradstreet, MCA-based registries and company websites.
A3: Google Maps (GMB) scraping was not possible from the research environment (Google was blocked by the network policy), so GMB-only businesses are not in this list yet.
A4: Owner names are rarely public. Where none was found, the column says 'Not listed - ask on call / MCA'. Check directors on the MCA portal (mca.gov.in) for Pvt Ltd companies.
A5: Justdial (08xxx / 09xxx 11-digit) and IndiaMART (+91 80xxx) numbers are virtual numbers that forward to the business. Ask for the direct mobile and WhatsApp on the first call.
A6: Directory data goes stale. Verify each number before relying on it; some listings are several years old (noted in the Pitch hook / Notes).
A7: National chains (Pepperfry, Wakefit, Royaloak, Damro, Livspace, D'LIFE) were left out on purpose: they have corporate websites and central marketing teams.
A9: Priority logic
A10: Hot = no website found + direct mobile or landline. Warm = has contact details (website already, or reachable only via virtual number). Cold = no public phone/email yet.
